{
    "Symbol": "NKE",
    "AssetType": "Common Stock",
    "Name": "Nike Inc",
    "Description": "Nike, Inc. is an American multinational corporation that is engaged in the design, development, manufacturing, and worldwide marketing and sales of footwear, apparel, equipment, accessories, and services. The company is headquartered near Beaverton, Oregon, in the Portland metropolitan area. It is the world's largest supplier of athletic shoes and apparel and a major manufacturer of sports equipment.",
    "CIK": "320187",
    "Exchange": "NYSE",
    "Currency": "USD",
    "Country": "USA",
    "Sector": "MANUFACTURING",
    "Industry": "RUBBER & PLASTICS FOOTWEAR",
    "Address": "ONE BOWERMAN DR, BEAVERTON, OR, US",
    "OfficialSite": "https://www.nike.com",
    "FiscalYearEnd": "May",
    "LatestQuarter": "2025-05-31",
    "MarketCapitalization": "107201151000",
    "EBITDA": "4516666000",
    "PERatio": "33.62",
    "PEGRatio": "2.751",
    "BookValue": "8.95",
    "DividendPerShare": "1.57",
    "DividendYield": "0.0225",
    "EPS": "2.16",
    "RevenuePerShareTTM": "31.19",
    "ProfitMargin": "0.0695",
    "OperatingMarginTTM": "0.0289",
    "ReturnOnAssetsTTM": "0.062",
    "ReturnOnEquityTTM": "0.233",
    "RevenueTTM": "46308999000",
    "GrossProfitTTM": "19790000000",
    "DilutedEPSTTM": "2.16",
    "QuarterlyEarningsGrowthYOY": "-0.859",
    "QuarterlyRevenueGrowthYOY": "-0.12",
    "AnalystTargetPrice": "75.71",
    "AnalystRatingStrongBuy": "5",
    "AnalystRatingBuy": "15",
    "AnalystRatingHold": "19",
    "AnalystRatingSell": "1",
    "AnalystRatingStrongSell": "1",
    "TrailingPE": "33.62",
    "ForwardPE": "41.32",
    "PriceToSalesRatioTTM": "2.315",
    "PriceToBookRatio": "8.11",
    "EVToRevenue": "2.355",
    "EVToEBITDA": "29.46",
    "Beta": "1.217",
    "52WeekHigh": "89.11",
    "52WeekLow": "51.93",
    "50DayMovingAverage": "63.57",
    "200DayMovingAverage": "71.46",
    "SharesOutstanding": "1178100000",
    "SharesFloat": "1160760000",
    "PercentInsiders": "1.715",
    "PercentInstitutions": "86.322",
    "DividendDate": "2025-07-01",
    "ExDividendDate": "2025-06-02"
}